pytket/extensions/iqm/__init__.py
pytket/extensions/iqm/_metadata.py
pytket/extensions/iqm/py.typed
pytket/extensions/iqm/backends/__init__.py
pytket/extensions/iqm/backends/config.py
pytket/extensions/iqm/backends/iqm.py
pytket_iqm-0.18.0.dist-info/licenses/LICENSE
tests/backend_test.py
tests/conftest.py
tests/convert_test.py
pytket_iqm-0.18.0.dist-info/METADATA
pytket_iqm-0.18.0.dist-info/WHEEL
pytket_iqm-0.18.0.dist-info/top_level.txt
pytket_iqm-0.18.0.dist-info/RECORD
