Metadata-Version: 2.4
Name: pytket-iqm
Version: 0.18.0
Summary: Extension for pytket, providing access to IQM backends
Author-email: TKET development team <tket-support@quantinuum.com>
Maintainer-email: TKET development team <tket-support@quantinuum.com>
License:                                  Apache License
Project-URL: documentation, https://tket.quantinuum.com/extensions/pytket-iqm/index.html
Project-URL: source, https://github.com/Quantinuum/pytket-iqm
Project-URL: tracker, https://github.com/Quantinuum/pytket-iqm/issues
Classifier: Environment :: Console
Classifier: Programming Language :: Python :: 3.10
Classifier: Programming Language :: Python :: 3.11
Classifier: Programming Language :: Python :: 3.12
Classifier: Programming Language :: Python :: 3.13
Classifier: Operating System :: MacOS :: MacOS X
Classifier: Operating System :: POSIX :: Linux
Classifier: Operating System :: Microsoft :: Windows
Classifier: Intended Audience :: Developers
Classifier: Intended Audience :: Science/Research
Classifier: Topic :: Scientific/Engineering
Requires-Python: <4.0,>=3.10
License-File: LICENSE
Requires-Dist: pytket>=2.11.0
Requires-Dist: iqm-client~=22.3
Dynamic: license-file
